setup.py
pili/__init__.py
pili/api.py
pili/auth.py
pili/conf.py
pili/errors.py
pili/hub.py
pili/stream.py
pili/utils.py
pili.egg-info/PKG-INFO
pili.egg-info/SOURCES.txt
pili.egg-info/dependency_links.txt
pili.egg-info/top_level.txt