Metadata-Version: 1.0
Name: pili
Version: 1.5.6
Summary: Pili Streaming Cloud server-side library for Python
Home-page: UNKNOWN
Author: Pili Engineering
Author-email: pili@qiniu.com
License: MIT License
Keywords: pili
Platform: any
